dj_smail/__init__.py
dj_smail/admin.py
dj_smail/apps.py
dj_smail/backends.py
dj_smail/exceptions.py
dj_smail/fields.py
dj_smail/forms.py
dj_smail/message.py
dj_smail/models.py
dj_smail/utils.py
dj_smail/version.py
dj_smail/views.py
dj_smail/crypto/__init__.py
dj_smail/crypto/crypto.py
dj_smail/crypto/encrypt.py
dj_smail/crypto/sign.py
dj_smail/migrations/0001_initial.py
dj_smail/migrations/__init__.py
dj_smail-0.7.0.dist-info/LICENSE
dj_smail-0.7.0.dist-info/METADATA
dj_smail-0.7.0.dist-info/WHEEL
dj_smail-0.7.0.dist-info/top_level.txt
dj_smail-0.7.0.dist-info/RECORD
